drhwrapper/__init__.py
drhwrapper/api.py
drhwrapper-0.1.1.dist-info/LICENSE
drhwrapper-0.1.1.dist-info/METADATA
drhwrapper-0.1.1.dist-info/WHEEL
drhwrapper-0.1.1.dist-info/top_level.txt
drhwrapper-0.1.1.dist-info/RECORD
