Metadata-Version: 2.1
Name: drhwrapper
Version: 0.1.1
Summary: A Python wrapper for the Database of Religious History API
Home-page: https://github.com/religionhistory/drhwrapper
Author: Victor Møller Poulsen
Author-email: victormoeller@gmail.com
License: Apache 2.0
Project-URL: Bug Tracker, https://github.com/religionhistory/drhwrapper/issues
Project-URL: Documentation, https://github.com/religionhistory/drhwrapper#readme
Project-URL: Source Code, https://github.com/religionhistory/drhwrapper
Project-URL: Demos, https://github.com/religionhistory/drhwrapper/tree/main/demo
Keywords: religion,history,api,wrapper
Classifier: Development Status :: 3 - Alpha
Classifier: Intended Audience :: Science/Research
Classifier: License :: OSI Approved :: Apache Software License
Classifier: Programming Language :: Python :: 3
Classifier: Programming Language :: Python :: 3.8
Classifier: Programming Language :: Python :: 3.9
Classifier: Programming Language :: Python :: 3.10
Classifier: Programming Language :: Python :: 3.11
Classifier: Programming Language :: Python :: 3.12
Classifier: Operating System :: OS Independent
Requires-Python: >=3.8
License-File: LICENSE
Requires-Dist: networkx>=3.0
Requires-Dist: numpy>=1.24.0
Requires-Dist: pandas>=2.0
Requires-Dist: requests>=2.27.0
Requires-Dist: tqdm
